k3fs/__init__.py
k3fs/fs.py
k3fs-0.1.10.dist-info/licenses/LICENSE
k3fs-0.1.10.dist-info/METADATA
k3fs-0.1.10.dist-info/WHEEL
k3fs-0.1.10.dist-info/top_level.txt
k3fs-0.1.10.dist-info/RECORD
